wwf/__init__.py
wwf/_nbdev.py
wwf/deployment.py
wwf/style_transfer.py
wwf/utils.py
wwf/basics/__init__.py
wwf/basics/interp.py
wwf/basics/training_loop.py
wwf/callback/__init__.py
wwf/callback/lr_find.py
wwf/tab/__init__.py
wwf/tab/export.py
wwf/tab/stats.py
wwf/vision/__init__.py
wwf/vision/timm.py
wwf/vision/object_detection/__init__.py
wwf/vision/object_detection/inference.py
wwf/vision/object_detection/metrics.py
wwf/vision/object_detection/model.py
wwf/vision/object_detection/utils.py
wwf-0.0.16.dist-info/METADATA
wwf-0.0.16.dist-info/RECORD
wwf-0.0.16.dist-info/WHEEL
wwf-0.0.16.dist-info/entry_points.txt
wwf-0.0.16.dist-info/top_level.txt
