Metadata-Version: 2.1
Name: wwf
Version: 0.0.16
Summary: The source code host for walkwithfastai.com
Home-page: https://github.com/walkwithfastai/walkwithfastai.github.io/tree/master/
Author: Zachary Mueller
Author-email: muellerzr@gmail.com
License: Apache Software License 2.0
Keywords: fastai fastai2 wwf2
Platform: UNKNOWN
Classifier: Development Status :: 3 - Alpha
Classifier: Intended Audience :: Developers
Classifier: License :: OSI Approved :: Apache Software License
Classifier: Natural Language :: English
Classifier: Programming Language :: Python :: 3.6
Classifier: Programming Language :: Python :: 3.7
Classifier: Programming Language :: Python :: 3.8
Requires-Python: >=3.6
Requires-Dist: fastai (>=2.0.0)
Requires-Dist: fastcore (>=1.0.0)
Requires-Dist: timm (>=0.3.4)
